PyEasier/PyEasier.py
PyEasier/__init__.py
PyEasier-0.0.6.2.dist-info/METADATA
PyEasier-0.0.6.2.dist-info/WHEEL
PyEasier-0.0.6.2.dist-info/top_level.txt
PyEasier-0.0.6.2.dist-info/RECORD
