Metadata-Version: 2.1
Name: PyEasier
Version: 0.0.6.2
Summary: This package makes you python experience better it includes nice shortcut functions to help solve problems in less lines of code.
Author: Yellow Yams(Vedic Mukherjee)
Author-email: "Yellow Yams(Vedic Mukherjee)" <yellowyams5@gmail.com>
Project-URL: Bug Tracker, https://github.com/YellowBoyYams/PyEasier/issues
Keywords: python,PyEasier,quick code,fast development,easy to use,build
Classifier: Programming Language :: Python :: 3
Classifier: License :: OSI Approved :: MIT License
Classifier: Operating System :: OS Independent
Requires-Python: >=3.7
Requires-Dist: py2app
Requires-Dist: pyinstaller
Requires-Dist: psutil
